datapipe_app/__init__.py
datapipe_app/api_v1alpha1.py
datapipe_app/api_v1alpha2.py
datapipe_app/cli.py
datapipe_app/datapipe_api.py
datapipe_app/frontend/asset-manifest.json
datapipe_app/frontend/favicon.ico
datapipe_app/frontend/index.html
datapipe_app/frontend/manifest.json
datapipe_app/frontend/robots.txt
datapipe_app/frontend/static/css/main.ef52a49f.css
datapipe_app/frontend/static/css/main.ef52a49f.css.map
datapipe_app/frontend/static/js/main.f5600965.js
datapipe_app/frontend/static/js/main.f5600965.js.LICENSE.txt
datapipe_app/frontend/static/js/main.f5600965.js.map
datapipe_app/frontend/static/media/db-icon.9befcb0d4eeb44fd922f.svg
datapipe_app/frontend/static/media/fn-icon.947c4ec9c8f529970e90.svg
datapipe_app/metrics.py
datapipe_app/models.py
datapipe_app/settings.py
datapipe_app-0.5.4.dist-info/LICENSE
datapipe_app-0.5.4.dist-info/METADATA
datapipe_app-0.5.4.dist-info/WHEEL
datapipe_app-0.5.4.dist-info/entry_points.txt
datapipe_app-0.5.4.dist-info/RECORD
