Metadata-Version: 2.1
Name: datapipe-app
Version: 0.5.4
Summary: 
Author: Andrey Tatarinov
Author-email: a@tatarinov.co
Requires-Python: >=3.9,<3.13
Classifier: Programming Language :: Python :: 3
Classifier: Programming Language :: Python :: 3.9
Classifier: Programming Language :: Python :: 3.10
Classifier: Programming Language :: Python :: 3.11
Classifier: Programming Language :: Python :: 3.12
Provides-Extra: gcp
Provides-Extra: jaeger
Requires-Dist: click (>=7.1.2)
Requires-Dist: datapipe-core (>=0.14.1,<0.15)
Requires-Dist: fastapi (>=0.69.0)
Requires-Dist: opentelemetry-exporter-gcp-trace (>=1.3.0,<2.0.0) ; extra == "gcp"
Requires-Dist: opentelemetry-exporter-jaeger (>=1.8.0,<2.0.0) ; extra == "jaeger"
Requires-Dist: opentelemetry-instrumentation-fastapi (>=0.35b0)
Requires-Dist: pydantic-settings (>=2.0.0)
Requires-Dist: rich (>=13.3.2,<14.0.0)
Requires-Dist: starlette-exporter
Requires-Dist: uvicorn[standard] (>=0.17.0)
